LICENSE
MANIFEST.in
README.md
pyproject.toml
setup.cfg
setup.py
wagtail_waffle/__init__.py
wagtail_waffle/apps.py
wagtail_waffle/bulk_actions.py
wagtail_waffle/views.py
wagtail_waffle/wagtail_hooks.py
wagtail_waffle.egg-info/PKG-INFO
wagtail_waffle.egg-info/SOURCES.txt
wagtail_waffle.egg-info/dependency_links.txt
wagtail_waffle.egg-info/requires.txt
wagtail_waffle.egg-info/top_level.txt
wagtail_waffle/migrations/__init__.py
wagtail_waffle/templates/waffle/action.html
wagtail_waffle/templates/waffle/index.html